odoo9_addon_website_sale_vat_required-9.0.1.0.0.99.dev1-py2.7-nspkg.pth
odoo9_addon_website_sale_vat_required-9.0.1.0.0.99.dev1.dist-info/DESCRIPTION.rst
odoo9_addon_website_sale_vat_required-9.0.1.0.0.99.dev1.dist-info/METADATA
odoo9_addon_website_sale_vat_required-9.0.1.0.0.99.dev1.dist-info/RECORD
odoo9_addon_website_sale_vat_required-9.0.1.0.0.99.dev1.dist-info/WHEEL
odoo9_addon_website_sale_vat_required-9.0.1.0.0.99.dev1.dist-info/metadata.json
odoo9_addon_website_sale_vat_required-9.0.1.0.0.99.dev1.dist-info/namespace_packages.txt
odoo9_addon_website_sale_vat_required-9.0.1.0.0.99.dev1.dist-info/top_level.txt
odoo_addons/website_sale_vat_required/README.rst
odoo_addons/website_sale_vat_required/__init__.py
odoo_addons/website_sale_vat_required/__openerp__.py
odoo_addons/website_sale_vat_required/controllers/__init__.py
odoo_addons/website_sale_vat_required/controllers/main.py
odoo_addons/website_sale_vat_required/demo/assets.xml
odoo_addons/website_sale_vat_required/static/description/icon.png
odoo_addons/website_sale_vat_required/static/src/js/website_sale.tour.js
